MANIFEST.in
setup.cfg
setup.py
versioneer.py
clyent/__init__.py
clyent/_version.py
clyent/errors.py
clyent.egg-info/PKG-INFO
clyent.egg-info/SOURCES.txt
clyent.egg-info/dependency_links.txt
clyent.egg-info/pbr.json
clyent.egg-info/top_level.txt
clyent/colors/__init__.py
clyent/colors/color.py
clyent/colors/color_formatter.py
clyent/logs/__init__.py
clyent/logs/handlers.py
clyent/logs/colors/__init__.py
clyent/logs/colors/printer.py
clyent/routes/__init__.py
clyent/tests/__init__.py
clyent/tests/test_clyent.py