Metadata-Version: 1.0
Name: clyent
Version: 1.0.1
Summary: Command line client Library for windwos and posix
Home-page: http://github.com/binstar/clyent
Author: Continuum Analytics
Author-email: srossross@gmail.com
License: BSD
Platform: UNKNOWN
